LICENSE.txt
MANIFEST.in
README.md
setup.py
undocker.py
undocker.egg-info/PKG-INFO
undocker.egg-info/SOURCES.txt
undocker.egg-info/dependency_links.txt
undocker.egg-info/entry_points.txt
undocker.egg-info/top_level.txt