Metadata-Version: 2.1
Name: undocker
Version: 7
Summary: Unpack docker images
Home-page: http://github.com/larsks/undocker
Author: Lars Kellogg-Stedman
Author-email: lars@oddbit.com
License: UNKNOWN
Platform: UNKNOWN
